TinderApi/__init__.py
TinderApi/browser.py
TinderApi/captcha.py
TinderApi/debugger.py
TinderApi/exceptions.py
TinderApi/session.py
TinderApi/tinder.py
TinderApi/utils.py
TinderApi/api/account.py
TinderApi/api/matches.py
TinderApi/api/media.py
TinderApi/api/misc.py
TinderApi/api/swipe.py
TinderApi/api/user.py
TinderApi/protos/authgateway.py
TinderApi/protos/create_placeholder_request.py
TinderApi/protos/create_placeholder_response_model.py
TinderApi/protos/media.py
TinderApi/protos/media_responses.py
TinderApi/protos/order_media_request.py
TinderApi/protos/order_media_response_model.py
MTinderApi-0.0.3.dist-info/LICENSE
MTinderApi-0.0.3.dist-info/METADATA
MTinderApi-0.0.3.dist-info/WHEEL
MTinderApi-0.0.3.dist-info/top_level.txt
MTinderApi-0.0.3.dist-info/RECORD
