Metadata-Version: 2.1
Name: MTinderApi
Version: 0.0.3
Summary: An unofficial api wrapper for tinder.
Author: cexyboy
License: MIT License        
Project-URL: Homepage, https://github.com/cexyboy/TinderApi
Project-URL: Bug Tracker, https://github.com/cexyboy/TinderApi/issues
Classifier: Programming Language :: Python :: 3.9
Requires-Python: >=3.8
License-File: LICENSE
